{"choeropsis-liberiensis":[6,6],"caracal-aurata":[8,9],"ozotoceros-bezoarticus":[7,5],"acinonyx-jubatus":[4,10],"nanger-dama":[7,4],"pan-troglodytes":[3,5],"madoqua-kirkii":[11,3],"acerodon-jubatus":[3,6],"capricornis-crispus":[6,8],"presbytis-comata":[3,9],"redunca-redunca":[6,9],"brachyteles-hypoxanthus":[7,5],"pagophilus-groenlandicus":[4,6],"arctocephalus-tropicalis":[4,5],"zalophus-californianus":[5,9],"pan-paniscus":[4,10],"cystophora-cristata":[4,3],"cephalophus-dorsalis":[6,8],"cephalophus-rufilatus":[4,6],"bos-javanicus":[9,5],"canis-rufus":[2,7],"tragelaphus-spekii":[7,6],"canis-simensis":[2,6],"madoqua-guentheri":[7,9],"tapirus-pinchaque":[7,6],"vicugna-vicugna":[6,3],"connochaetes-gnou":[6,3],"hippocamelus-bisulcus":[7,4],"rhinoceros-unicornis":[9,3],"equus-quagga":[5,4],"monachus-monachus":[4,6],"leontopithecus-caissara":[5,9],"leopardus-jacobita":[3,9],"cephalophus-natalensis":[6,6],"tragelaphus-angasii":[11,5],"vulpes-vulpes":[6,5],"monachus-schauinslandi":[5,5],"urocyon-littoralis":[7,3],"alces-alces":[6,1],"aepyceros-melampus":[10,3],"tragelaphus-imberbis":[7,4],"pteropus-rufus":[4,6],"cuon-alpinus":[7,4],"bubalus-mindorensis":[6,7],"hapalemur-alaotrensis":[4,6],"saiga-tatarica":[4,5],"equus-feruscaballus":[6,5],"hydrurga-leptonyx":[5,4],"capra-falconeri":[9,8],"pardofelis-badia":[7,5],"bubalus-bubalis":[9,3],"pardofelis-marmorata":[5,6],"melursus-ursinus":[6,5],"cephalophus-zebra":[7,5],"hapalemur-aureus":[4,10],"arabitragus-jayakari":[7,5],"pongo-abelii":[3,10],"hippotragus-niger":[5,3],"arctocephalus-australis":[5,4],"pongo-pygmaeus":[4,6],"ovis-dalli":[5,3],"tragelaphus-scriptus":[5,4],"neophoca-cinerea":[5,7],"beatragus-hunteri":[5,3],"rungwecebus-kipunji":[5,3],"pteropus-livingstonii":[3,5],"hippotragus-equinus":[7,7],"gazella-subgutturosa":[7,6],"muntiacus-crinifrons":[3,8],"otaria-flavescens":[7,5],"equus-kiang":[3,6],"oreotragus-oreotragus":[8,7],"cephalophus-niger":[5,11],"pteronura-brasiliensis":[7,10],"propithecus-candidus":[6,11],"crocuta-crocuta":[7,8],"c-lupusfamiliaris":[4,1],"ursus-americanus":[7,5],"philantomba-monticola":[6,4],"propithecus-tattersalli":[6,5],"tragelaphus-strepsiceros":[11,6],"antilope-cervicapra":[5,6],"tragelaphus-eurycerus":[6,7],"eudorcas-thomsonii":[11,3],"felis-catus":[9,8],"bos-gaurus":[5,4],"oryx-leucoryx":[8,5],"gazella-leptoceros":[8,5],"ovis-aries":[7,5],"tapirus-indicus":[6,8],"ourebia-ourebi":[5,4],"leontopithecus-chrysopygus":[5,4],"tragelaphus-oryx":[9,3],"cephalophus-harveyi":[8,7],"cryptoprocta-ferox":[3,5],"cephalophus-ogilbyi":[4,6],"hippopotamus-amphibius":[6,6],"phoca-vitulina":[4,10],"kobus-ellipsiprymnus":[8,6],"pseudalopex-fulvipes":[5,12],"lycaon-pictus":[10,5],"dama-mesopotamica":[7,3],"speothos-venaticus":[4,6],"macaca-pagensis":[8,6],"rhinopithecus-bieti":[5,3],"mirounga-leonina":[2,4],"macaca-silenus":[3,10],"nanger-soemmerringii":[6,5],"arctocephalus-townsendi":[6,11],"lama-guanicoe":[7,6],"pteropus-niger":[4,5],"prolemur-simus":[6,5],"raphicerus-sharpei":[7,6],"leptonychotes-weddellii":[4,6],"halichoerus-grypus":[4,9],"f-silvestrisbieti":[5,5],"trachypithecus-geei":[5,6],"hylobates-moloch":[4,4],"eumetopias-jubatus":[7,4],"redunca-arundinum":[4,6],"capra-aegagrushircus":[8,4],"lynx-lynx":[4,5],"hylobates-muelleri":[4,4],"myotis-sodalis":[5,7],"leontopithecus-rosalia":[4,8],"zalophus-wollebaeki":[7,6],"cephalophus-callipygus":[7,6],"equus-zebra":[5,1],"ursus-arctos":[4,6],"hyaena-brunnea":[5,6],"bos-primigeniustaurus":[7,3],"callorhinus-ursinus":[5,9],"lobodon-carcinophaga":[5,3],"capra-caucasica":[6,4],"nomascus-hainanus":[4,5],"axis-calamianensis":[5,3],"ailurus-fulgens":[6,7],"catagonus-wagneri":[5,4],"arctocephalus-forsteri":[6,8],"kobus-leche":[7,5],"rusa-timorensis":[5,6],"cephalophus-silvicultor":[6,7],"bubalus-arnee":[4,3],"panthera-uncia":[5,6],"antilocapra-americana":[6,1],"redunca-fulvorufula":[5,7],"tapirus-bairdii":[4,3],"ailuropoda-melanoleuca":[6,4],"equus-africanusasinus":[6,4],"arctocephalus-philippii":[5,9],"pteropus-poliocephalus":[4,6],"loris-tardigradus":[4,8],"nilgiritragus-hylocrius":[6,4],"leopardus-guigna":[3,6],"kobus-vardonii":[5,7],"nomascus-concolor":[3,6],"mustela-nigripes":[5,4],"tragelaphus-derbianus":[4,5],"equus-grevyi":[6,5],"rucervus-duvaucelii":[6,6],"chrysocyon-brachyurus":[5,6],"mirounga-angustirostris":[7,4],"neotragus-batesi":[7,10],"alcelaphus-buselaphus":[7,7],"rhinopithecus-strykeri":[5,7],"hippocamelus-antisensis":[4,6],"oryx-beisa":[8,5],"axis-kuhlii":[9,3],"galidictis-grandidieri":[4,8],"pelea-capreolus":[7,6],"arctocephalus-galapagoensis":[2,6],"gorilla-beringei":[9,5],"nesotragus-moschatus":[5,6],"macroderma-gigas":[5,6],"ursus-maritimus":[4,5],"brachyteles-arachnoides":[2,5],"philantomba-maxwellii":[4,3],"oryx-gazella":[7,7],"connochaetes-taurinus":[7,3],"equus-asinusxequuscaballus":[5,6],"diceros-bicornis":[4,8],"ceratotherium-simum":[3,7],"capra-pyrenaica":[8,6],"capra-nubiana":[8,4],"mystacina-tuberculata":[3,3],"arctocephalus-pusillus":[4,4],"oreamnos-americanus":[5,2],"lycalopex-sechurae":[5,6],"sylvicapra-grimmia":[5,7],"pteropus-rodricensis":[4,6],"cephalophus-nigrifrons":[5,4],"porcula-salvania":[3,9],"raphicerus-campestris":[7,5],"gazella-gazella":[7,1],"lynx-pardinus":[4,5],"capreolus-pygargus":[8,3],"procapra-gutturosa":[7,8],"gorilla-gorilla":[7,8],"bos-mutus":[6,9],"litocranius-walleri":[7,3],"equus-africanus":[6,2],"naemorhedus-baileyi":[6,5],"bison-bonasus":[7,1],"okapia-johnstoni":[6,5],"madoqua-saltiana":[2,8],"pseudoryx-nghetinhensis":[6,8],"leontopithecus-chrysomelas":[3,7],"neofelis-nebulosa":[5,10],"giraffa-camelopardalis":[4,5],"neofelis-diardi":[6,8],"lontra-felina":[4,7],"antidorcas-marsupialis":[3,5],"phocarctos-hookeri":[5,6],"rusa-alfredi":[6,7],"equus-ferusprzewalskii":[4,5],"nanger-granti":[5,5],"prionailurus-bengalensisiriomotensis":[2,4],"eudorcas-rufifrons":[5,2],"propithecus-perrieri":[3,5],"theropithecus-gelada":[5,4],"addax-nasomaculatus":[6,4],"panthera-pardus":[4,10],"kobus-megaceros":[4,3],"cephalophus-jentinki":[4,9],"cercocebus-sanjei":[4,7],"panthera-leo":[5,7],"hyemoschus-aquaticus":[4,10],"equus-hemionus":[7,9],"procyon-pygmaeus":[6,9],"prionailurus-rubiginosus":[5,9],"capra-ibex":[8,2],"pudu-puda":[6,4],"procapra-przewalskii":[6,5],"trachypithecus-johnii":[2,7],"procolobus-kirkii":[4,6],"camelus-ferus":[9,5],"macaca-maura":[5,6],"bison-bison":[7,5],"ommatophoca-rossii":[3,7],"capra-walie":[7,4],"dicerorhinus-sumatrensis":[4,5],"macaca-sylvanus":[4,5],"syncerus-caffer":[7,3],"pusa-sibirica":[6,4],"pusa-hispidasaimensis":[5,7],"homo-sapienssapiens":[8,4],"neotragus-pygmaeus":[6,4],"cebus-flavius":[3,6],"ammotragus-lervia":[4,5],"panthera-tigris":[2,7],"rhinoceros-sondaicus":[7,7],"sus-scrofadomesticus":[6,4],"nyctalus-azoreum":[4,3],"tragelaphus-buxtoni":[1,3],"tetracerus-quadricornis":[6,3],"saguinus-oedipus":[2,5],"gazella-cuvieri":[2,4],"enhydra-lutris":[3,5],"hyaena-hyaena":[3,5]}